Metadata-Version: 1.0
Name: pdistrib
Version: 0.1.2
Summary: Probability Distributions
Home-page: UNKNOWN
Author: UNKNOWN
Author-email: UNKNOWN
License: UNKNOWN
Platform: UNKNOWN
